MANIFEST.in
setup.cfg
setup.py
md2slide/README.md
md2slide/Tutorial.md
md2slide/__init__.py
md2slide/__main__.py
md2slide/control.css
md2slide/control.js
md2slide/remark-20160618.min.js
md2slide/server.py
md2slide/slide.css
md2slide.egg-info/PKG-INFO
md2slide.egg-info/SOURCES.txt
md2slide.egg-info/dependency_links.txt
md2slide.egg-info/entry_points.txt
md2slide.egg-info/top_level.txt