Metadata-Version: 1.1
Name: md2slide
Version: 0.0.3
Summary: A web server serve markdown file to html slide
Home-page: https://github.com/yanganto/MD2Slide
Author: yanganto
Author-email: yanganto@gmail.com
License: MIT
Keywords: markdown,slide
Platform: UNKNOWN
Classifier: Programming Language :: Python
Classifier: Programming Language :: Python :: 3
Classifier: Topic :: Internet :: WWW/HTTP :: HTTP Servers
